mms_networkx-1.12rc1.data/data/share/doc/networkx-1.12rc1/INSTALL.txt
mms_networkx-1.12rc1.data/data/share/doc/networkx-1.12rc1/LICENSE.txt
mms_networkx-1.12rc1.data/data/share/doc/networkx-1.12rc1/examples/3d_drawing/mayavi2_spring.py
mms_networkx-1.12rc1.data/data/share/doc/networkx-1.12rc1/examples/advanced/eigenvalues.py
mms_networkx-1.12rc1.data/data/share/doc/networkx-1.12rc1/examples/advanced/heavy_metal_umlaut.py
mms_networkx-1.12rc1.data/data/share/doc/networkx-1.12rc1/examples/advanced/iterated_dynamical_systems.py
mms_networkx-1.12rc1.data/data/share/doc/networkx-1.12rc1/examples/advanced/parallel_betweenness.py
mms_networkx-1.12rc1.data/data/share/doc/networkx-1.12rc1/examples/algorithms/blockmodel.py
mms_networkx-1.12rc1.data/data/share/doc/networkx-1.12rc1/examples/algorithms/davis_club.py
mms_networkx-1.12rc1.data/data/share/doc/networkx-1.12rc1/examples/algorithms/hartford_drug.edgelist
mms_networkx-1.12rc1.data/data/share/doc/networkx-1.12rc1/examples/algorithms/krackhardt_centrality.py
mms_networkx-1.12rc1.data/data/share/doc/networkx-1.12rc1/examples/algorithms/rcm.py
mms_networkx-1.12rc1.data/data/share/doc/networkx-1.12rc1/examples/basic/properties.py
mms_networkx-1.12rc1.data/data/share/doc/networkx-1.12rc1/examples/basic/read_write.py
mms_networkx-1.12rc1.data/data/share/doc/networkx-1.12rc1/examples/drawing/atlas.py
mms_networkx-1.12rc1.data/data/share/doc/networkx-1.12rc1/examples/drawing/chess_masters.py
mms_networkx-1.12rc1.data/data/share/doc/networkx-1.12rc1/examples/drawing/chess_masters_WCC.pgn.bz2
mms_networkx-1.12rc1.data/data/share/doc/networkx-1.12rc1/examples/drawing/circular_tree.py
mms_networkx-1.12rc1.data/data/share/doc/networkx-1.12rc1/examples/drawing/degree_histogram.py
mms_networkx-1.12rc1.data/data/share/doc/networkx-1.12rc1/examples/drawing/edge_colormap.py
mms_networkx-1.12rc1.data/data/share/doc/networkx-1.12rc1/examples/drawing/ego_graph.py
mms_networkx-1.12rc1.dist-info/LICENSE.txt
mms_networkx-1.12rc1.dist-info/METADATA
mms_networkx-1.12rc1.dist-info/WHEEL
mms_networkx-1.12rc1.dist-info/top_level.txt
mms_networkx-1.12rc1.dist-info/RECORD
